kapre/__init__.py
kapre/augmentation.py
kapre/backend.py
kapre/backend_keras.py
kapre/filterbank.py
kapre/time_frequency.py
kapre/utils.py
kapre-0.1.4.dist-info/METADATA
kapre-0.1.4.dist-info/RECORD
kapre-0.1.4.dist-info/WHEEL
kapre-0.1.4.dist-info/top_level.txt
